rag_engine/__init__.py
rag_engine/database.py
rag_engine/embeddings.py
rag_engine/rag.py
rag_engine/utils.py
rag_engine-0.1.2.dist-info/LICENSE
rag_engine-0.1.2.dist-info/METADATA
rag_engine-0.1.2.dist-info/WHEEL
rag_engine-0.1.2.dist-info/top_level.txt
rag_engine-0.1.2.dist-info/RECORD
