Metadata-Version: 2.1
Name: rag_engine
Version: 0.1.2
Summary: A Retrieval-Augmented Generation (RAG) Engine for managing embeddings and similarity search
Home-page: https://github.com/slava-vishnyakov/rag_engine
Author: Slava Vishnyakov
Author-email: bomboze@gmail.com
Classifier: Development Status :: 3 - Alpha
Classifier: Intended Audience :: Developers
Classifier: License :: OSI Approved :: MIT License
Classifier: Operating System :: OS Independent
Classifier: Programming Language :: Python :: 3
Classifier: Programming Language :: Python :: 3.7
Classifier: Programming Language :: Python :: 3.8
Classifier: Programming Language :: Python :: 3.9
Classifier: Programming Language :: Python :: 3.10
Requires-Python: >=3.7
License-File: LICENSE
Requires-Dist: openai >=1.0.0
Requires-Dist: sqlite-vec >=0.1.0
Requires-Dist: python-dotenv >=0.19.0
Provides-Extra: dev
Requires-Dist: bump2version >=1.0.1 ; extra == 'dev'
Requires-Dist: pytest >=6.2.5 ; extra == 'dev'
Requires-Dist: pytest-asyncio >=0.14.0 ; extra == 'dev'
